CHANGELOG.rst
MANIFEST.in
README.rst
setup.py
samplepy/__init__.py
samplepy/base.py
samplepy/importance.py
samplepy/metropolis_hastings.py
samplepy/rejection.py
samplepy.egg-info/PKG-INFO
samplepy.egg-info/SOURCES.txt
samplepy.egg-info/dependency_links.txt
samplepy.egg-info/requires.txt
samplepy.egg-info/top_level.txt
samplepy.egg-info/zip-safe
samplepy/examples/Impfig_1.png
samplepy/examples/MHfig_1.png
samplepy/examples/Rejfig_1.png
samplepy/examples/Rejfig_2.png
samplepy/examples/example_run.py
samplepy/tests/__init__.py
samplepy/tests/test_importance.py
samplepy/tests/test_mh.py
samplepy/tests/test_rejection.py