Metadata-Version: 1.1
Name: samplepy
Version: 1.0.11
Summary: sampling from univariate distributions
Home-page: http://github.com/elena-sharova/samplepy
Author: Elena Sharova
Author-email: UNKNOWN
License: MIT
Keywords: sampling rejection importance Metropolis-Hastings
Platform: UNKNOWN
Classifier: Development Status :: 3 - Alpha
Classifier: License :: OSI Approved :: MIT License
Classifier: Programming Language :: Python :: 2.7
Classifier: Topic :: Scientific/Engineering :: Mathematics
